[
  {
    "id": 134936,
    "nombre": "ACCIÓN INTEGRAL DE RIESGOS"
  },
  {
    "id": 136203,
    "nombre": "SEGUROS COMERCIALES BOLIVAR S.A.",
    "nit": "860002180-7"
  },
  {
    "id": 136204,
    "nombre": "COMPAÑIA DE SEGUROS BOLIVAR S.A.",
    "nit": "860002503-2"
  },
  {
    "id": 136205,
    "nombre": "LIBERTY SEGUROS S.A.",
    "nit": "860039988-0"
  },
  {
    "id": 136206,
    "nombre": "SEGUROS DE VIDA SURAMERICANA S.A.",
    "nit": "890903790-5"
  },
  {
    "id": 136207,
    "nombre": "SEGUROS DEL ESTADO S.A.",
    "nit": "860009578-6"
  },
  {
    "id": 136208,
    "nombre": "SBS SEGUROS COLOMBIA S.A.",
    "nit": "860026182-5"
  },
  {
    "id": 136209,
    "nombre": "ARL SURAMERICANA",
    "nit": "800256161-9"
  },
  {
    "id": 136210,
    "nombre": "EMERMEDICA",
    "nit": "800126785-1"
  },
  {
    "id": 136211,
    "nombre": "ALLIANZ SEGUROS S.A.",
    "nit": "891700037-9"
  },
  {
    "id": 136212,
    "nombre": "AXA COLPATRIA SEGUROS DE VIDA S.A.",
    "nit": "860002183-9"
  },
  {
    "id": 136213,
    "nombre": "MAPFRE SEGUROS S.A.",
    "nit": "860002400-0"
  },
  {
    "id": 136214,
    "nombre": "MAPFRE COLOMBIA VIDA SEGUROS S.A.",
    "nit": "830054904-6"
  },
  {
    "id": 136215,
    "nombre": "LA PREVISORA S.A.",
    "nit": "860037707-9"
  },
  {
    "id": 136216,
    "nombre": "CHUBB SEGUROS COLOMBIA S.A.",
    "nit": "860026518-6"
  },
  {
    "id": 136218,
    "nombre": "HDI SEGUROS S.A.",
    "nit": "860004875-6"
  },
  {
    "id": 136219,
    "nombre": "MAPFRE SERVICIOS EXEQUIALES S.A.S.",
    "nit": "900621719-6"
  },
  {
    "id": 136220,
    "nombre": "AXA COLPATRIA SEGUROS S.A",
    "nit": "860002184-6"
  },
  {
    "id": 136222,
    "nombre": "SEGUROS DE VIDA DEL ESTADO S.A.",
    "nit": "860009174-4"
  },
  {
    "id": 136223,
    "nombre": "SEGUROS GENERALES SURAMERICANA S.A.",
    "nit": "890903407-9"
  },
  {
    "id": 136224,
    "nombre": "ALLIANZ SEGUROS DE VIDA S.A.",
    "nit": "860027404-1"
  },
  {
    "id": 136225,
    "nombre": "METLIFE COLOMBIA SEGUROS DE VIDA S.A.",
    "nit": "860002398-5"
  },
  {
    "id": 136226,
    "nombre": "JMALUCELLI TRAVELRES SEGUROS S.A.",
    "nit": "900488151-3"
  },
  {
    "id": 158332,
    "nombre": "HDI SEGUROS COLOMBIA S.A.",
    "nit": "860039988-0"
  },
  {
    "id": 165657,
    "nombre": "QUALITAS COMPAÑIA DE SEGUROS COLOMBIA S.A.",
    "nit": "901849037-5"
  },
  {
    "id": 171795,
    "nombre": "COMPAÑIA MUNDIAL DE SEGUROS S.A.",
    "nit": "860037013-6"
  },
  {
    "id": 185435,
    "nombre": "LIBERTY COLOMBIA COMPAÑIA DE SEGUROS S.A.",
    "nit": "900488151-3"
  }
]